[
    {
        "key": "dbln",
        "value": "%7B%2261571488623051%22%3A%225Wy545nz%22%7D",
        "domain": "facebook.com",
        "path": "/login/device-based/",
        "hostOnly": false,
        "creation": "2025-01-21T06:41:12.572Z",
        "lastAccessed": "2025-01-21T06:41:12.572Z"
    },
    {
        "key": "datr",
        "value": "ETKOZ_SXU2rO-2lD25Qp3E9N",
        "domain": "facebook.com",
        "path": "/",
        "hostOnly": false,
        "creation": "2025-01-21T06:41:12.572Z",
        "lastAccessed": "2025-01-21T06:41:12.573Z"
    },
    {
        "key": "sb",
        "value": "ETKOZwpoePr7tUjquZPeI7Wz",
        "domain": "facebook.com",
        "path": "/",
        "hostOnly": false,
        "creation": "2025-01-21T06:41:12.573Z",
        "lastAccessed": "2025-01-21T06:41:12.573Z"
    },
    {
        "key": "locale",
        "value": "vi_VN",
        "domain": "facebook.com",
        "path": "/",
        "hostOnly": false,
        "creation": "2025-01-21T06:41:12.573Z",
        "lastAccessed": "2025-01-21T06:41:12.573Z"
    },
    {
        "key": "vpd",
        "value": "v1%3B719x393x2.75",
        "domain": "facebook.com",
        "path": "/",
        "hostOnly": false,
        "creation": "2025-01-21T06:41:12.573Z",
        "lastAccessed": "2025-01-21T06:41:12.573Z"
    },
    {
        "key": "ps_l",
        "value": "1",
        "domain": "facebook.com",
        "path": "/",
        "hostOnly": false,
        "creation": "2025-01-21T06:41:12.573Z",
        "lastAccessed": "2025-01-21T06:41:12.573Z"
    },
    {
        "key": "ps_n",
        "value": "1",
        "domain": "facebook.com",
        "path": "/",
        "hostOnly": false,
        "creation": "2025-01-21T06:41:12.573Z",
        "lastAccessed": "2025-01-21T06:41:12.573Z"
    },
    {
        "key": "c_user",
        "value": "61571488623051",
        "domain": "facebook.com",
        "path": "/",
        "hostOnly": false,
        "creation": "2025-01-21T06:41:12.573Z",
        "lastAccessed": "2025-01-21T06:41:12.573Z"
    },
    {
        "key": "fr",
        "value": "0nn90lzLiT6jqmkml.AWXBbT0D9zVgx8sRJFw7zRgUoGQ.BnjjIR..AAA.0.0.Bnju52.AWUkLqKZ00U",
        "domain": "facebook.com",
        "path": "/",
        "hostOnly": false,
        "creation": "2025-01-21T06:41:12.573Z",
        "lastAccessed": "2025-01-21T06:41:12.573Z"
    },
    {
        "key": "xs",
        "value": "3%3AHQdFi3s-6vcCTg%3A2%3A1737420406%3A-1%3A-1",
        "domain": "facebook.com",
        "path": "/",
        "hostOnly": false,
        "creation": "2025-01-21T06:41:12.573Z",
        "lastAccessed": "2025-01-21T06:41:12.573Z"
    },
    {
        "key": "m_pixel_ratio",
        "value": "2.75",
        "domain": "facebook.com",
        "path": "/",
        "hostOnly": false,
        "creation": "2025-01-21T06:41:12.573Z",
        "lastAccessed": "2025-01-21T06:41:12.573Z"
    },
    {
        "key": "wd",
        "value": "393x719",
        "domain": "facebook.com",
        "path": "/",
        "hostOnly": false,
        "creation": "2025-01-21T06:41:12.573Z",
        "lastAccessed": "2025-01-21T06:41:12.573Z"
    },
    {
        "key": "fbl_st",
        "value": "101631510%3BT%3A28957361",
        "domain": "facebook.com",
        "path": "/",
        "hostOnly": false,
        "creation": "2025-01-21T06:41:12.573Z",
        "lastAccessed": "2025-01-21T06:41:12.573Z"
    },
    {
        "key": "wl_cbv",
        "value": "v2%3Bclient_version%3A2716%3Btimestamp%3A1737441667",
        "domain": "facebook.com",
        "path": "/",
        "hostOnly": false,
        "creation": "2025-01-21T06:41:12.573Z",
        "lastAccessed": "2025-01-21T06:41:12.573Z"
    }
]
